MANIFEST.in
README.txt
setup.py
collective/__init__.py
collective.blueprint.jsonmigrator.egg-info/PKG-INFO
collective.blueprint.jsonmigrator.egg-info/SOURCES.txt
collective.blueprint.jsonmigrator.egg-info/dependency_links.txt
collective.blueprint.jsonmigrator.egg-info/entry_points.txt
collective.blueprint.jsonmigrator.egg-info/namespace_packages.txt
collective.blueprint.jsonmigrator.egg-info/not-zip-safe
collective.blueprint.jsonmigrator.egg-info/requires.txt
collective.blueprint.jsonmigrator.egg-info/top_level.txt
collective/blueprint/__init__.py
collective/blueprint/jsonmigrator/__init__.py
collective/blueprint/jsonmigrator/blueprint.py
collective/blueprint/jsonmigrator/configure.zcml
collective/blueprint/jsonmigrator/tests.py
collective/blueprint/jsonmigrator/version.txt