Metadata-Version: 1.0
Name: collective.blueprint.jsonmigrator
Version: 0.1.1
Summary: useful transmogrifier blueprints for large migrations from Plone, from 2.0 to 4.0
Home-page: http://svn.plone.org/svn/collective/
Author: UNKNOWN
Author-email: UNKNOWN
License: GPL
Platform: UNKNOWN
Classifier: Framework :: Plone
Classifier: Programming Language :: Python
